PyReadLabels/__init__.py
PyReadLabels/pyreadlabels.py
PyReadLabels/yolov3-tiny-label.cfg
PyReadLabels/yolov3-tiny-label_84.weights
PyReadLabels-1.1.5.dist-info/LICENSE
PyReadLabels-1.1.5.dist-info/METADATA
PyReadLabels-1.1.5.dist-info/WHEEL
PyReadLabels-1.1.5.dist-info/top_level.txt
PyReadLabels-1.1.5.dist-info/RECORD
