Metadata-Version: 2.1
Name: PyReadLabels
Version: 1.1.5
Summary: Python Package to read labels from image
Home-page: https://github.com/santhtadi/PyReadLabels
Author: santh kumar tadi
Author-email: santhtadi@gmail.com
License: MIT
Platform: UNKNOWN
Classifier: Programming Language :: Python :: 3
Classifier: License :: OSI Approved :: MIT License
Classifier: Operating System :: OS Independent
Requires-Python: >=3.4
Requires-Dist: opencv-python
Requires-Dist: numpy
